{
  "project_info": {
    "project_number": "154658331931",
    "project_id": "sport-partner-7e9c9",
    "storage_bucket": "sport-partner-7e9c9.appspot.com"
  },
  "client": [
    {
      "client_info": {
        "mobilesdk_app_id": "1:154658331931:android:71dda7c9805e1ce92947be",
        "android_client_info": {
          "package_name": "com.example.sport_partner2"
        }
      },
      "oauth_client": [
        {
          "client_id": "154658331931-8paa5ddnrqudd9b0p9pcnjv2pt4bm19t.apps.googleusercontent.com",
          "client_type": 3
        }
      ],
      "api_key": [
        {
          "current_key": "AIzaSyBL7ci_OqMFTv40STuZRhGNWgjHibARewc"
        }
      ],
      "services": {
        "appinvite_service": {
          "other_platform_oauth_client": [
            {
              "client_id": "154658331931-8paa5ddnrqudd9b0p9pcnjv2pt4bm19t.apps.googleusercontent.com",
              "client_type": 3
            }
          ]
        }
      }
    }
  ],
  "configuration_version": "1"
}